didacto/__init__.py
didacto/__main__.py
didacto/controller.py
didacto/main.py
didacto/model.py
didacto/view.py
Didacto-0.1.10.dist-info/LICENSE
Didacto-0.1.10.dist-info/METADATA
Didacto-0.1.10.dist-info/WHEEL
Didacto-0.1.10.dist-info/top_level.txt
Didacto-0.1.10.dist-info/RECORD
