Metadata-Version: 2.1
Name: Didacto
Version: 0.1.10
Summary: Indexing pdf corpora keywords fields
Home-page: https://gitlab.inubo.ch/glag/didacto
Author: Marco de Freitas
Author-email: marco@silage.ch
License: LICENSE.txt
Platform: UNKNOWN
Requires-Python: >=3.5
Requires-Dist: PyPDF2 (>=1.26.0)
